modelscope_gradio_components/__init__.py
modelscope_gradio_components/components/Chatbot/__init__.py
modelscope_gradio_components/components/Chatbot/__init__.pyi
modelscope_gradio_components/components/Chatbot/llm_thinking_presets.py
modelscope_gradio_components/components/Chatbot/templates/component/index.js
modelscope_gradio_components/components/Chatbot/templates/component/style.css
modelscope_gradio_components/components/Chatbot/templates/example/index.js
modelscope_gradio_components/components/Chatbot/templates/example/style.css
modelscope_gradio_components/components/Markdown/__init__.py
modelscope_gradio_components/components/Markdown/__init__.pyi
modelscope_gradio_components/components/Markdown/templates/component/index.js
modelscope_gradio_components/components/Markdown/templates/component/style.css
modelscope_gradio_components/components/Markdown/templates/example/index.js
modelscope_gradio_components/components/Markdown/templates/example/style.css
modelscope_gradio_components/components/MultimodalInput/__init__.py
modelscope_gradio_components/components/MultimodalInput/__init__.pyi
modelscope_gradio_components/components/MultimodalInput/templates/component/__vite-browser-external-2447137e.js
modelscope_gradio_components/components/MultimodalInput/templates/component/index.js
modelscope_gradio_components/components/MultimodalInput/templates/component/style.css
modelscope_gradio_components/components/MultimodalInput/templates/component/wrapper-6f348d45-f837cf34.js
modelscope_gradio_components/components/MultimodalInput/templates/example/index.js
modelscope_gradio_components/components/MultimodalInput/templates/example/style.css
modelscope_gradio_components/utils/__init__.py
modelscope_gradio_components/utils/process_links.py
modelscope_gradio_components-0.0.1b10.dist-info/METADATA
modelscope_gradio_components-0.0.1b10.dist-info/WHEEL
modelscope_gradio_components-0.0.1b10.dist-info/licenses/LICENSE
modelscope_gradio_components-0.0.1b10.dist-info/RECORD
